{
	"info": {
		"_postman_id": "2967308a-f8aa-4c13-b2d8-3d93b1ab6db1",
		"name": "Category",
		"schema": "https://schema.getpostman.com/json/collection/v2.1.0/collection.json"
	},
	"item": [
		{
			"name": "getCategories",
			"request": {
				"method": "GET",
				"header": [],
				"url": {
					"raw": "http://localhost:8082/category",
					"protocol": "http",
					"host": [
						"localhost"
					],
					"port": "8082",
					"path": [
						"category"
					]
				}
			},
			"response": []
		},
		{
			"name": "getCategory",
			"request": {
				"method": "GET",
				"header": [],
				"url": {
					"raw": "http://localhost:8082/category/1",
					"protocol": "http",
					"host": [
						"localhost"
					],
					"port": "8082",
					"path": [
						"category",
						"1"
					]
				}
			},
			"response": []
		},
		{
			"name": "createCategory",
			"request": {
				"method": "POST",
				"header": [],
				"body": {
					"mode": "raw",
					"raw": "{\r\n    \"category\": \"Farmacia\"\r\n}",
					"options": {
						"raw": {
							"language": "json"
						}
					}
				},
				"url": {
					"raw": "http://localhost:8082/category",
					"protocol": "http",
					"host": [
						"localhost"
					],
					"port": "8082",
					"path": [
						"category"
					]
				}
			},
			"response": []
		},
		{
			"name": "updateCategory",
			"request": {
				"method": "PUT",
				"header": [],
				"body": {
					"mode": "raw",
					"raw": "{\r\n    \"category\": \"Abarrotes\"\r\n}",
					"options": {
						"raw": {
							"language": "json"
						}
					}
				},
				"url": {
					"raw": "http://localhost:8082/category/1",
					"protocol": "http",
					"host": [
						"localhost"
					],
					"port": "8082",
					"path": [
						"category",
						"1"
					]
				}
			},
			"response": []
		},
		{
			"name": "deleteCategory",
			"request": {
				"method": "DELETE",
				"header": [],
				"url": {
					"raw": "http://localhost:8082/category/1",
					"protocol": "http",
					"host": [
						"localhost"
					],
					"port": "8082",
					"path": [
						"category",
						"1"
					]
				}
			},
			"response": []
		}
	]
}